[
  {
    "id": "weekly-2026-w29",
    "week": "2026-W29",
    "title": "研究網站與工具整理週報",
    "dateRange": "2026-07-13 ~ 2026-07-19",
    "summary": "本週主要完成 Blog 分類與標籤系統，並開始建立任務與週報系統第一版。",
    "completed": [
      "完成文章 category 與 tags 欄位整理",
      "建立 /categories 與 /tags 頁面",
      "在 /blog 加入分類快速篩選"
    ],
    "progress": [
      "網站逐漸從研究日誌轉向研究管理系統",
      "開始規劃每日任務、每週任務與週報的資料結構"
    ],
    "problems": [
      "目前任務與週報仍需手動修改 JSON 檔案",
      "尚未加入登入與後台編輯功能"
    ],
    "solutions": [
      "第一版先使用靜態資料確認版面與資料格式",
      "等功能穩定後再考慮 Cloudflare D1 或後台編輯"
    ],
    "unfinished": [
      "任務狀態尚未能在網站上直接編輯",
      "週報尚未能自動從任務資料產生"
    ],
    "next": [
      "測試 /tasks 與 /weekly 頁面",
      "思考是否要加入任務篩選功能",
      "後續規劃登入與資料庫版本"
    ],
    "categories": ["網站開發", "研究整理"],
    "tags": ["Astro", "任務管理", "週報"]
  }
]
